pyheroicons/__init__.py
pyheroicons/icons/optimized/16/solid/academic-cap.svg
pyheroicons/icons/optimized/16/solid/adjustments-horizontal.svg
pyheroicons/icons/optimized/16/solid/adjustments-vertical.svg
pyheroicons/icons/optimized/16/solid/archive-box-arrow-down.svg
pyheroicons/icons/optimized/16/solid/archive-box-x-mark.svg
pyheroicons/icons/optimized/16/solid/archive-box.svg
pyheroicons/icons/optimized/16/solid/arrow-down-circle.svg
pyheroicons/icons/optimized/16/solid/arrow-down-left.svg
pyheroicons/icons/optimized/16/solid/arrow-down-on-square-stack.svg
pyheroicons/icons/optimized/16/solid/arrow-down-on-square.svg
pyheroicons/icons/optimized/16/solid/arrow-down-right.svg
pyheroicons/icons/optimized/16/solid/arrow-down-tray.svg
pyheroicons/icons/optimized/16/solid/arrow-down.svg
pyheroicons/icons/optimized/16/solid/arrow-left-circle.svg
pyheroicons/icons/optimized/16/solid/arrow-left-end-on-rectangle.svg
pyheroicons/icons/optimized/16/solid/arrow-left-start-on-rectangle.svg
pyheroicons/icons/optimized/16/solid/arrow-left.svg
pyheroicons/icons/optimized/16/solid/arrow-long-down.svg
pyheroicons/icons/optimized/16/solid/arrow-long-left.svg
pyheroicons/icons/optimized/16/solid/arrow-long-right.svg
pyheroicons/icons/optimized/16/solid/arrow-long-up.svg
pyheroicons/icons/optimized/16/solid/arrow-path-rounded-square.svg
pyheroicons/icons/optimized/16/solid/arrow-path.svg
pyheroicons/icons/optimized/16/solid/arrow-right-circle.svg
pyheroicons/icons/optimized/16/solid/arrow-right-end-on-rectangle.svg
pyheroicons/icons/optimized/16/solid/arrow-right-start-on-rectangle.svg
pyheroicons/icons/optimized/16/solid/arrow-right.svg
pyheroicons/icons/optimized/16/solid/arrow-top-right-on-square.svg
pyheroicons/icons/optimized/16/solid/arrow-trending-down.svg
pyheroicons/icons/optimized/16/solid/arrow-trending-up.svg
pyheroicons/icons/optimized/16/solid/arrow-up-circle.svg
pyheroicons/icons/optimized/16/solid/arrow-up-left.svg
pyheroicons-1.2.0.dist-info/LICENSE
pyheroicons-1.2.0.dist-info/METADATA
pyheroicons-1.2.0.dist-info/WHEEL
pyheroicons-1.2.0.dist-info/top_level.txt
pyheroicons-1.2.0.dist-info/RECORD
